README.md
setup.py
amoveo/__init__.py
amoveo/client.py
amoveo/excepts.py
amoveo/explorer.py
amoveo/node.py
amoveo/serializer.py
amoveo/sign.py
amoveo_client.egg-info/PKG-INFO
amoveo_client.egg-info/SOURCES.txt
amoveo_client.egg-info/dependency_links.txt
amoveo_client.egg-info/not-zip-safe
amoveo_client.egg-info/requires.txt
amoveo_client.egg-info/top_level.txt