Metadata-Version: 1.2
Name: amoveo-client
Version: 0.2.0
Summary: amoveo python client
Home-page: https://github.com/dmitry1981/amoveo-client
Author: Dmitry Zhidkih
Author-email: zhidkih.dmitry@gmail.com
License: MIT
Keywords: amoveo veo
Platform: UNKNOWN
Requires-Python: >=3.6,<4
